data_lelo/__init__.py
data_lelo/finance_data.py
data_lelo-0.0.3.dist-info/METADATA
data_lelo-0.0.3.dist-info/WHEEL
data_lelo-0.0.3.dist-info/top_level.txt
data_lelo-0.0.3.dist-info/RECORD
