Metadata-Version: 2.1
Name: data-lelo
Version: 0.0.3
Summary: Fetch market data for the NSE Exchange
Home-page: UNKNOWN
Author: Abhishek Mittal
Author-email: abhishekmittal964@gmail.com
License: UNKNOWN
Keywords: python,finance,NSE,data,market,trading,investing
Platform: UNKNOWN
Classifier: Development Status :: 1 - Planning
Classifier: Intended Audience :: Developers
Classifier: Programming Language :: Python :: 3
Classifier: Operating System :: Unix
Classifier: Operating System :: MacOS :: MacOS X
Classifier: Operating System :: Microsoft :: Windows
Requires-Dist: requests
Requires-Dist: python-dotenv
Requires-Dist: datetime
Requires-Dist: os
